PDNPR
