Metadata-Version: 2.1
Name: PDNPR
Version: 0.1.1
Summary: Tool to find allosteric route based on MD files
Author: Spencer Wang
Author-email: jrwangspencer@stu.suda.edu.cn
Keywords: Python,Protein,allosteric,Network,Shortest route,windows,mac,linux
Classifier: Development Status :: 1 - Planning
Classifier: Intended Audience :: Developers
Classifier: Programming Language :: Python :: 3
Classifier: Operating System :: Unix
Classifier: Operating System :: MacOS :: MacOS X
Classifier: Operating System :: Microsoft :: Windows
Requires-Python: >=3.9
License-File: LICENSE
Requires-Dist: networkx
Requires-Dist: tqdm
Requires-Dist: mdtraj
Requires-Dist: contourpy==1.2.1
Requires-Dist: cycler==0.12.1
Requires-Dist: fonttools==4.51.0
Requires-Dist: kiwisolver==1.4.5
Requires-Dist: matplotlib==3.9.0
Requires-Dist: pillow==10.3.0
Provides-Extra: tk
